{
    "structure": {
        "meta": {
            "isoCore": false,
            "createdAt": "2019-03-08T12:56:36.329Z",
            "updatedAt": "2019-03-21T10:22:17.223Z",
            "publishedAt": null,
            "contentExpiresAt": null,
            "keywords": [],
            "chapters": [
                "cha_Ek89ib9LI"
            ],
            "status": "draft",
            "modifiedBy": "GuillaumeLafon",
            "createdBy": "GuillaumeLafon"
        },
        "ref": "sli_E1G0XUi88",
        "universalRef": "sli_E1G0XUi88",
        "position": 0,
        "klf": "klf",
        "tips": "tips",
        "clue": null,
        "question": {
            "type": "qcmGraphic",
            "header": "header",
            "explanation": "explanation",
            "medias": [],
            "content": {
                "choices": [
                    {
                        "id": "sli_E1G0XUi88.choice_N1e~QVUoIL.id",
                        "label": "choice_N1e~QVUoIL",
                        "value": "choice_N1e~QVUoIL",
                        "media": "med_N1~74LsIL"
                    },
                    {
                        "id": "sli_E1G0XUi88.choice_E1eEXVUi88.id",
                        "label": "choice_E1eEXVUi88",
                        "value": "choice_E1eEXVUi88",
                        "media": "med_VyV7EIoIL"
                    },
                    {
                        "id": "sli_E1G0XUi88.choice_Eyx57EUoL8.id",
                        "label": "choice_Eyx57EUoL8",
                        "value": "choice_Eyx57EUoL8",
                        "media": "med_4JcQV8oUL"
                    },
                    {
                        "id": "sli_E1G0XUi88.choice_N1eDVNIoLU.id",
                        "label": "choice_N1eDVNIoLU",
                        "value": "choice_N1eDVNIoLU",
                        "media": "med_EJwEEIo8I"
                    }
                ],
                "answers": [
                    [
                        "choice_E1eEXVUi88"
                    ]
                ]
            }
        }
    },
    "locales": {
        "en": {
            "header": "Which of the following locutions is the most related to the concept of Memento mori?",
            "explanation": "Select the correct answer.",
            "klf": "Memento mori is quite similar to the ‘<i>Carpe Diem</i>’ mindset. In both cases, you start with the consciousness of your limited time on Earth to finally realise that every day, every hour, and every minute matters. But these philosophies differ in their practice: At the opposite of <i>Carpe Diem</i>, Memento mori enjoins you to make choices by asking how you'd like to be remembered at your own funeral.",
            "tips": "Death may well mean we no longer worry about how people remember us but a positive lasting legacy is something to consider to help meet your larger goals, and can help you prioritise what is important to you.",
            "clue": "",
            "context_title": "",
            "context_description": "",
            "context_media_description": "",
            "choice_N1e~QVUoIL": "Yolo",
            "choice_E1eEXVUi88": "Carpe Diem",
            "choice_Eyx57EUoL8": "Thug life",
            "choice_N1eDVNIoLU": "Alea Jacta est"
        },
        "fr": {
            "header": "Laquelle des locutions suivantes est la plus liée au concept de Memento mori ?",
            "explanation": "Sélectionnez la bonne réponse.",
            "klf": "Memento mori est assez similaire à l'état d'esprit <i>Carpe Diem</i>. Dans les deux cas, vous commencez avec la conscience de votre temps limité sur Terre pour enfin réaliser que chaque jour, chaque heure et chaque minute compte. Mais ces philosophies diffèrent dans leur pratique : à l’inverse de <i>Carpe Diem</i> , Memento mori vous enjoint de faire des choix en vous demandant comment vous aimeriez que l’on se souvienne de vous lors de vos propres funérailles.",
            "tips": "La mort peut très bien signifier que nous n'avons plus à nous inquiéter de la façon dont les gens se souviennent de nous, mais désirer laisser un héritage positif et durable peut vous aider à atteindre vos objectifs plus larges, et à privilégier ce qui est important pour vous.",
            "clue": "",
            "context_title": "",
            "context_description": "",
            "context_media_description": "",
            "choice_N1e~QVUoIL": "Yolo",
            "choice_E1eEXVUi88": "Carpe Diem",
            "choice_Eyx57EUoL8": "Thug life",
            "choice_N1eDVNIoLU": "Alea Jacta est"
        },
        "de": {
            "header": "Which of the following locutions is the most related to the concept of Memento mori?",
            "explanation": "Select the correct answer.",
            "klf": "Memento mori is quite similar to the ‘<i>Carpe Diem</i>’ mindset. In both cases, you start with the consciousness of your limited time on Earth to finally realise that every day, every hour, and every minute matters. But these philosophies differ in their practice: At the opposite of <i>Carpe Diem</i>, Memento mori enjoins you to make choices by asking how you'd like to be remembered at your own funeral.",
            "tips": "Death may well mean we no longer worry about how people remember us but a positive lasting legacy is something to consider to help meet your larger goals, and can help you prioritise what is important to you.",
            "clue": "",
            "context_title": "",
            "context_description": "",
            "context_media_description": "",
            "choice_N1e~QVUoIL": "Yolo",
            "choice_E1eEXVUi88": "Carpe Diem",
            "choice_Eyx57EUoL8": "Thug life",
            "choice_N1eDVNIoLU": "Alea Jacta est"
        },
        "th": {
            "header": "Which of the following locutions is the most related to the concept of Memento mori?",
            "explanation": "Select the correct answer.",
            "klf": "Memento mori is quite similar to the ‘<i>Carpe Diem</i>’ mindset. In both cases, you start with the consciousness of your limited time on Earth to finally realise that every day, every hour, and every minute matters. But these philosophies differ in their practice: At the opposite of <i>Carpe Diem</i>, Memento mori enjoins you to make choices by asking how you'd like to be remembered at your own funeral.",
            "tips": "Death may well mean we no longer worry about how people remember us but a positive lasting legacy is something to consider to help meet your larger goals, and can help you prioritise what is important to you.",
            "clue": "",
            "context_title": "",
            "context_description": "",
            "context_media_description": "",
            "choice_N1e~QVUoIL": "Yolo",
            "choice_E1eEXVUi88": "Carpe Diem",
            "choice_Eyx57EUoL8": "Thug life",
            "choice_N1eDVNIoLU": "Alea Jacta est"
        }
    }
}
