{
    "structure": {
        "meta": {
            "isoCore": false,
            "createdAt": "2018-10-11T11:56:05.702Z",
            "updatedAt": "2018-11-09T12:32:42.309Z",
            "publishedAt": null,
            "contentExpiresAt": null,
            "keywords": [],
            "chapters": [
                "cha_V1m6r84cr"
            ],
            "status": "draft",
            "modifiedBy": "Auxanealc",
            "createdBy": "ThereseG"
        },
        "ref": "sli_NyJQYQd5r",
        "universalRef": "sli_NyJQYQd5r",
        "position": 0,
        "klf": "klf",
        "tips": "tips",
        "clue": null,
        "question": {
            "type": "qcm",
            "header": "header",
            "explanation": "explanation",
            "medias": [],
            "content": {
                "choices": [
                    {
                        "id": "sli_NyJQYQd5r.choice_N1K4YQ-qB.id",
                        "label": "choice_N1K4YQ-qB",
                        "value": "choice_N1K4YQ-qB"
                    },
                    {
                        "id": "sli_NyJQYQd5r.choice_NJzrt7ucB.id",
                        "label": "choice_NJzrt7ucB",
                        "value": "choice_NJzrt7ucB"
                    },
                    {
                        "id": "sli_NyJQYQd5r.choice_E12SYmu9r.id",
                        "label": "choice_E12SYmu9r",
                        "value": "choice_E12SYmu9r"
                    }
                ],
                "answers": [
                    [
                        "choice_N1K4YQ-qB",
                        "choice_NJzrt7ucB"
                    ]
                ]
            }
        }
    },
    "locales": {
        "en": {
            "header": "What characteristics do champions share?",
            "explanation": "Select the correct answers.",
            "klf": "Once the champions are on board, they’ll do everything they can to help you. Their enthusiasm and eagerness will encourage others to get with the programme.",
            "tips": "The word enthusiasm originates in the Greek word <i>enthous</i>, meaning ‘possessed by a god, inspired’, based on <i>theos</i> which means ‘god’. The actual meaning is slightly different: ‘Intense and eager enjoyment, interest, or approval’.",
            "clue": "",
            "context_title": "",
            "context_description": "",
            "context_media_description": "",
            "choice_N1K4YQ-qB": "They are enthusiastic",
            "choice_NJzrt7ucB": "They are willing to go the extra mile",
            "choice_E12SYmu9r": "They champion change for their personal benefit"
        },
        "fr": {
            "header": "Quelles sont les caractéristiques communes aux champions ?",
            "explanation": "Sélectionnez les bonnes réponses.",
            "klf": "Une fois les champions à vos côtés, ils feront tout leur possible pour vous aider. Grâce à leur enthousiasme et leur empressement, ils encourageront les autres à adhérer au programme.",
            "tips": "Le mot enthousiasme vient du grec <i>enthous</i>, « inspiration ou possession divine », provenant de <i>theos</i> qui signifie « dieu ». La signification réelle est légèrement différente : « Joie très vive, tendant à s’extérioriser et exprimant une adhésion totale, une approbation complète ».",
            "clue": "",
            "context_title": "",
            "context_description": "",
            "context_media_description": "",
            "choice_N1K4YQ-qB": "Ils sont enthousiastes",
            "choice_NJzrt7ucB": "Ils ont la volonté d’en faire plus",
            "choice_E12SYmu9r": "Ils œuvrent en faveur du changement pour leur propre intérêt"
        },
        "de": {
            "header": "Welche Eigenschaften haben Champions gemeinsam?",
            "explanation": "Wählen Sie die richtigen Antworten aus.",
            "klf": "Sobald die Champions an Bord sind, werden sie alles tun, um Ihnen zu helfen. Ihre Begeisterung und Eifer werden andere dazu ermutigen, sich mit dem Programm zu beschäftigen.",
            "tips": "Das Wort &quot;Begeisterung&quot; stammt aus dem griechischen Wort &quot; <i>enthusiastisch&quot;</i> und bedeutet &quot;besessen von einem Gott, inspiriert&quot;, basierend auf <i>theos,</i> was &quot;Gott&quot; bedeutet. Die tatsächliche Bedeutung ist etwas anders: &quot;Intensiver und eifriger Genuss, Interesse oder Anerkennung&quot;.",
            "clue": "",
            "context_title": "",
            "context_description": "",
            "context_media_description": "",
            "choice_N1K4YQ-qB": "Sie sind begeistert",
            "choice_NJzrt7ucB": "Sie sind bereit, die Extrameile zu gehen",
            "choice_E12SYmu9r": "Sie setzen sich zu ihrem persönlichen Vorteil für Veränderungen ein"
        },
        "th": {
            "header": "What characteristics do champions share?",
            "explanation": "Select the correct answers.",
            "klf": "Once the champions are on board, they’ll do everything they can to help you. Their enthusiasm and eagerness will encourage others to get with the programme.",
            "tips": "The word enthusiasm originates in the Greek word <i>enthous</i>, meaning ‘possessed by a god, inspired’, based on <i>theos</i> which means ‘god’. The actual meaning is slightly different: ‘Intense and eager enjoyment, interest, or approval’.",
            "clue": "",
            "context_title": "",
            "context_description": "",
            "context_media_description": "",
            "choice_N1K4YQ-qB": "They are enthusiastic",
            "choice_NJzrt7ucB": "They are willing to go the extra mile",
            "choice_E12SYmu9r": "They champion change for their personal benefit"
        }
    }
}
