{
    "structure": {
        "meta": {
            "isoCore": false,
            "createdAt": "2019-06-05T15:35:58.354Z",
            "updatedAt": "2019-06-05T15:35:58.354Z",
            "publishedAt": null,
            "contentExpiresAt": null,
            "keywords": [],
            "slides": [
                "sli_V16HM1tjI",
                "sli_NyHAf1toU",
                "sli_41UjmkYiL",
                "sli_V1pOEyKjL"
            ],
            "chapters": [],
            "modifiedBy": "Margaux-Schmitt",
            "createdBy": "Margaux-Schmitt"
        },
        "ref": "les_4J08g0eRI",
        "position": 0,
        "poster": "med_Nk3dlAlCL",
        "description": "description",
        "resource": "med_41MvgAl0I"
    },
    "locales": {
        "en": {
            "description": "The home team advantage"
        },
        "fr": {
            "description": "L'avantage de jouer à domicile"
        },
        "de": {
            "description": "The home team advantage"
        },
        "th": {
            "description": "The home team advantage"
        }
    }
}
