{
    "structure": {
        "meta": {
            "isoCore": false,
            "createdAt": "2018-10-25T15:32:40.234Z",
            "updatedAt": "2018-11-12T11:02:29.153Z",
            "publishedAt": null,
            "contentExpiresAt": null,
            "keywords": [],
            "slides": [
                "sli_EynV2PecS",
                "sli_NJh06wgqS",
                "sli_41M32l45H",
                "sli_V1vD5WVqr"
            ],
            "chapters": [],
            "status": "draft",
            "modifiedBy": "Margaux-Schmitt",
            "createdBy": "Margaux-Schmitt"
        },
        "ref": "les_EJRYg05oB",
        "position": 2,
        "poster": "med_NyNoe05sB",
        "description": "description",
        "resource": "med_V1jqxAcjH"
    },
    "locales": {
        "en": {
            "description": "Avoid the ego barrier"
        },
        "fr": {
            "description": "Éviter le piège de l’égo"
        },
        "de": {
            "description": "Vermeiden Sie die Ego-Barriere"
        },
        "th": {
            "description": "หลีกเลี่ยงอุปสรรคจากอัตตา"
        }
    }
}
