{
    "structure": {
        "meta": {
            "isoCore": false,
            "createdAt": "2019-05-17T08:02:47.616Z",
            "updatedAt": "2019-05-17T08:02:47.616Z",
            "publishedAt": null,
            "contentExpiresAt": null,
            "keywords": [],
            "slides": [
                "sli_41w4SL4YL",
                "sli_N1ZgILNY8",
                "sli_4kLtUU4tU",
                "sli_E1xk-U4FI"
            ],
            "chapters": [],
            "modifiedBy": "Margaux-Schmitt",
            "createdBy": "Margaux-Schmitt"
        },
        "ref": "les_EkL3tIPhI",
        "position": 0,
        "poster": "med_Nk6hKIw2U",
        "description": "description",
        "resource": "med_4Jt2KIDhU"
    },
    "locales": {
        "en": {
            "description": "Get introduced"
        },
        "fr": {
            "description": "Être présenté"
        },
        "de": {
            "description": "Get introduced"
        },
        "th": {
            "description": "Get introduced"
        }
    }
}
