{
    "structure": {
        "meta": {
            "isoCore": false,
            "createdAt": "2019-01-09T15:06:18.945Z",
            "updatedAt": "2019-03-19T17:05:56.823Z",
            "publishedAt": null,
            "taggedNewUntil": "2019-03-21T15:04:37.951Z",
            "contentExpiresAt": null,
            "keywords": [],
            "status": "draft",
            "modifiedBy": "Margaux-Schmitt",
            "createdBy": "CharlotteRitzmann"
        },
        "ref": "dis_4yIs2lyf8",
        "universalRef": "dis_4yIs2lyf8",
        "name": "name",
        "partnershipType": "paidpartner",
        "position": 0,
        "hidden": false,
        "draft": false,
        "cover": {
            "coverDescription": "coverDescription",
            "resource": null,
            "poster": "med_VyO4g3zEL"
        },
        "courses": [],
        "thematiques": [],
        "partners": [
            "part_V18SxMYsr"
        ],
        "conditions": [],
        "version": "2",
        "states": {
            "en": {
                "edition": "validate"
            },
            "fr": {
                "edition": "validate"
            },
            "de": {
                "edition": "validate"
            },
            "th": {
                "edition": "draft"
            }
        }
    },
    "locales": {
        "en": {
            "name": "Practical wellbeing",
            "coverDescription": "Do you feel like you don't have enough time to take care of your own wellbeing? The pressures of work and the hectic pace of modern living can mean that we sometimes neglect ourselves and overlook our basic needs to eat, sleep, and have downtime. This course will show you how to take care of yourself, and how showing kindness to others and focusing on one task at a time can reduce stress and improve working relationships."
        },
        "fr": {
            "name": "Améliorer votre bien-être physique",
            "coverDescription": "Avez-vous l'impression de manquer de temps pour vous occuper de votre propre bien-être ? La pression liée au travail et le rythme trépidant de notre vie moderne nous empêchent parfois de prendre soin de nous-mêmes et nous conduisent à négliger nos besoins fondamentaux que sont l'alimentation, le sommeil et la détente. Ce cours va vous démontrer que prendre soin de vous-même, faire preuve de bienveillance envers les autres et vous concentrer sur une seule tâche à la fois contribuent à réduire votre stress et à améliorer vos relations au travail."
        },
        "de": {
            "name": "Praktisches Wohlbefinden",
            "coverDescription": "Haben Sie das Gefühl, dass Sie nicht genug Zeit haben, sich um Ihr Wohlbefinden zu kümmern? Der Druck auf die Arbeit und die Hektik des modernen Lebens können dazu führen, dass wir uns manchmal vernachlässigen und unsere Grundbedürfnisse wie Essen, Schlaf und Ruhezeiten übersehen. Dieser Kurs zeigt Ihnen, wie Sie auf sich selbst aufpassen können und wie Sie Freundlichkeit demonstrieren und sich auf eine Aufgabe konzentrieren können, um Stress abzubauen und die Arbeitsbeziehungen zu verbessern."
        },
        "th": {
            "name": "Practical wellbeing",
            "coverDescription": "Do you feel like you don't have enough time to take care of your own wellbeing? The pressures of work and the hectic pace of modern living can mean that we sometimes neglect ourselves and overlook our basic needs to eat, sleep, and have downtime. This course will show you how to take care of yourself, and how showing kindness to others and focusing on one task at a time can reduce stress and improve working relationships."
        }
    }
}
