{
    "structure": {
        "meta": {
            "isoCore": false,
            "createdAt": "2019-06-21T14:27:00.000Z",
            "updatedAt": "2019-06-21T14:27:00.000Z",
            "publishedAt": null,
            "contentExpiresAt": null,
            "keywords": [],
            "modifiedBy": "MarinPostel",
            "createdBy": "MarinPostel"
        },
        "ref": "med_NkDr-ASyD",
        "type": "img",
        "src": [
            {
                "filename": "filename_EyeXUdCBkP",
                "mimeType": "image/jpeg",
                "mediaUrl": "mediaUrl_4JmIdAB1w",
                "tmp": {}
            }
        ]
    },
    "locales": {
        "en": {
            "filename_EyeXUdCBkP": "False.jpg",
            "mediaUrl_4JmIdAB1w": "//static.coorpacademy.com/content/CoorpAcademy/content-video-arts/cockpit-video-arts/default/false-1561127218140.jpg"
        },
        "fr": {
            "mediaUrl_4JmIdAB1w": "//static.coorpacademy.com/content/CoorpAcademy/content-video-arts/cockpit-video-arts/default/false-1561127218140.jpg",
            "filename_EyeXUdCBkP": "False.jpg"
        },
        "de": {
            "mediaUrl_4JmIdAB1w": "//static.coorpacademy.com/content/CoorpAcademy/content-video-arts/cockpit-video-arts/default/false-1561127218140.jpg",
            "filename_EyeXUdCBkP": "False.jpg"
        },
        "th": {
            "filename_EyeXUdCBkP": "False.jpg",
            "mediaUrl_4JmIdAB1w": "//static.coorpacademy.com/content/CoorpAcademy/content-video-arts/cockpit-video-arts/default/false-1561127218140.jpg"
        }
    }
}
