{
    "_deleted": true,
    "structure": {
        "meta": {
            "isoCore": true,
            "createdAt": "2018-09-10T09:48:17.474Z",
            "updatedAt": "2018-09-10T09:48:17.474Z",
            "publishedAt": null,
            "contentExpiresAt": null,
            "keywords": [],
            "status": "draft",
            "modifiedBy": "ValentineMichaud",
            "createdBy": "ValentineMichaud",
            "coreBranch": "dunod"
        },
        "ref": "med_NyyJp7J-H",
        "type": "img",
        "src": [
            {
                "filename": "filename_4keHJ6mkOB",
                "mimeType": "image/jpeg",
                "mediaUrl": "mediaUrl_Ekryp7y-B",
                "tmp": {}
            }
        ]
    },
    "locales": {
        "fr": {
            "filename_4keHJ6mkOB": "veille.jpg",
            "mediaUrl_Ekryp7y-B": "//static.coorpacademy.com/content/CoorpAcademy/content-dunod/cockpit-dunod/default/veille-1536572867844.jpg"
        },
        "en": {
            "filename_4keHJ6mkOB": "veille.jpg",
            "mediaUrl_Ekryp7y-B": "//static.coorpacademy.com/content/CoorpAcademy/content-dunod/cockpit-dunod/default/veille-1536572867844.jpg"
        }
    }
}
