{
    "structure": {
        "meta": {
            "isoCore": false,
            "createdAt": "2019-01-24T15:09:17.751Z",
            "updatedAt": "2019-01-24T15:09:17.751Z",
            "publishedAt": null,
            "contentExpiresAt": null,
            "keywords": [],
            "status": "draft",
            "modifiedBy": "ThereseG",
            "createdBy": "ThereseG"
        },
        "ref": "med_N1YME6fQU",
        "type": "img",
        "src": [
            {
                "filename": "filename_E1e-4VTMmL",
                "mimeType": "image/jpeg",
                "mediaUrl": "mediaUrl_NyuNNpf7U",
                "tmp": {}
            }
        ]
    },
    "locales": {
        "en": {
            "filename_E1e-4VTMmL": "shutterstock_162830552.jpg",
            "mediaUrl_NyuNNpf7U": "//static.coorpacademy.com/content/CoorpAcademy/content-video-arts/cockpit-video-arts/default/shutterstock_162830552-1548342552090.jpg"
        },
        "fr": {
            "mediaUrl_NyuNNpf7U": "//static.coorpacademy.com/content/CoorpAcademy/content-video-arts/cockpit-video-arts/default/shutterstock_162830552-1548342552090.jpg",
            "filename_E1e-4VTMmL": "shutterstock_162830552.jpg"
        },
        "de": {
            "mediaUrl_NyuNNpf7U": "//static.coorpacademy.com/content/CoorpAcademy/content-video-arts/cockpit-video-arts/default/shutterstock_162830552-1548342552090.jpg",
            "filename_E1e-4VTMmL": "shutterstock_162830552.jpg"
        },
        "th": {
            "filename_E1e-4VTMmL": "shutterstock_162830552.jpg",
            "mediaUrl_NyuNNpf7U": "//static.coorpacademy.com/content/CoorpAcademy/content-video-arts/cockpit-video-arts/default/shutterstock_162830552-1548342552090.jpg"
        }
    }
}
