{
    "structure": {
        "meta": {
            "isoCore": false,
            "createdAt": "2018-10-19T09:26:18.752Z",
            "updatedAt": "2018-12-05T14:15:11.444Z",
            "publishedAt": null,
            "contentExpiresAt": null,
            "keywords": [],
            "status": "draft",
            "modifiedBy": "Margaux-Schmitt",
            "createdBy": "Margaux-Schmitt"
        },
        "ref": "med_Nk0BMqMir",
        "type": "img",
        "src": [
            {
                "filename": "filename_VJlLIf5fjr",
                "mediaUrl": "mediaUrl_EyL8MqMjS",
                "tmp": {}
            }
        ]
    },
    "locales": {
        "en": {
            "mediaUrl_EyL8MqMjS": "//static.coorpacademy.com/content/CoorpAcademy/content-video-arts/cockpit-video-arts/default/entrust-people-with-big-responsibilities-1544019302649.png",
            "filename_VJlLIf5fjr": "Entrust people with big responsibilities.png"
        },
        "fr": {
            "mediaUrl_EyL8MqMjS": "//static.coorpacademy.com/content/CoorpAcademy/content-video-arts/cockpit-video-arts/default/themed_poster-light-1539941172276.jpg",
            "filename_VJlLIf5fjr": "themed_poster-light.jpg"
        },
        "de": {
            "mediaUrl_EyL8MqMjS": "//static.coorpacademy.com/content/CoorpAcademy/content-video-arts/cockpit-video-arts/default/entrust-people-with-big-responsibilities-1544019302649.png",
            "filename_VJlLIf5fjr": "Entrust people with big responsibilities.png"
        },
        "th": {
            "mediaUrl_EyL8MqMjS": "//static.coorpacademy.com/content/CoorpAcademy/content-video-arts/cockpit-video-arts/default/entrust-people-with-big-responsibilities-1544019302649.png",
            "filename_VJlLIf5fjr": "Entrust people with big responsibilities.png"
        }
    }
}
