{
    "structure": {
        "meta": {
            "isoCore": true,
            "createdAt": "2016-03-02T09:01:34.636Z",
            "updatedAt": "2016-03-02T09:01:34.636Z",
            "publishedAt": null,
            "contentExpiresAt": null,
            "keywords": [],
            "status": "draft",
            "modifiedBy": "Hortensel",
            "createdBy": "Hortensel",
            "coreBranch": "test-trad"
        },
        "ref": "med_4yOtt5Jnx",
        "type": "img",
        "format": "choice",
        "src": [
            {
                "filename": "filename_41gA2qc1hl",
                "mimeType": "image/jpeg",
                "mediaUrl": "mediaUrl_4JA3c5k2g"
            }
        ]
    },
    "locales": {
        "fr": {
            "filename_41gA2qc1hl": "Afrique du Sud.jpg",
            "mediaUrl_4JA3c5k2g": "//static.coorpacademy.com/content/partner-au-feminin/fr/medias/img/choice/afrique-du-sud-1456909213735.jpg"
        },
        "en": {
            "mediaUrl_4JA3c5k2g": "//static.coorpacademy.com/content/partner-au-feminin/fr/medias/img/choice/afrique-du-sud-1456909213735.jpg",
            "filename_41gA2qc1hl": "Afrique du Sud.jpg"
        },
        "de": {
            "mediaUrl_4JA3c5k2g": "//static.coorpacademy.com/content/partner-au-feminin/en/medias/img/choice/afrique-du-sud-1456909213735.jpg",
            "filename_41gA2qc1hl": "Afrique du Sud.jpg"
        },
        "es": {
            "filename_41gA2qc1hl": "Afrique du Sud.jpg",
            "mediaUrl_4JA3c5k2g": "//static.coorpacademy.com/content/partner-au-feminin/en/medias/img/choice/afrique-du-sud-1456909213735.jpg"
        },
        "zh": {
            "mediaUrl_4JA3c5k2g": "//static.coorpacademy.com/content/partner-au-feminin/en/medias/img/choice/afrique-du-sud-1456909213735.jpg",
            "filename_41gA2qc1hl": "Afrique du Sud.jpg"
        }
    }
}
